README.md
setup.py
pysphero/__init__.py
pysphero/constants.py
pysphero/core.py
pysphero/driving.py
pysphero/exceptions.py
pysphero/helpers.py
pysphero/packet.py
pysphero/utils.py
pysphero.egg-info/PKG-INFO
pysphero.egg-info/SOURCES.txt
pysphero.egg-info/dependency_links.txt
pysphero.egg-info/requires.txt
pysphero.egg-info/top_level.txt
pysphero/bluetooth/__init__.py
pysphero/bluetooth/ble_adapter.py
pysphero/bluetooth/bluepy_adapter.py
pysphero/bluetooth/gatt_adapter.py
pysphero/bluetooth/packet_collector.py
pysphero/device_api/__init__.py
pysphero/device_api/animatronics.py
pysphero/device_api/api_processor.py
pysphero/device_api/device_api.py
pysphero/device_api/peer_connection.py
pysphero/device_api/power.py
pysphero/device_api/proto.py
pysphero/device_api/secondary_mcu_firmware_update.py
pysphero/device_api/sensor.py
pysphero/device_api/system_info.py
pysphero/device_api/system_mode.py
pysphero/device_api/user_io.py
pysphero/device_api/wifi_command.py