Metadata-Version: 2.1
Name: pysphero
Version: 0.0.12
Summary: Unofficial library for sphero v2.
Home-page: https://github.com/EnotYoyo/pysphero
Author: Andrey Lemets
Author-email: a.a.lemets@gmail.com
License: MIT License
Keywords: sphero,sphero-ble,bolt
Platform: UNKNOWN
Classifier: Development Status :: 3 - Alpha
Classifier: Topic :: Software Development :: Libraries
Classifier: License :: OSI Approved :: MIT License
Classifier: Operating System :: Unix
Classifier: Programming Language :: Python :: 3.6
Classifier: Programming Language :: Python :: 3.7
Provides-Extra: tests
Provides-Extra: gatt
